[
    {
        "accuracy": 0.2733,
        "batch": 128,
        "duration": 127963552209,
        "lr": 0.06686484516516415,
        "momentum": 0.7450304069365566,
        "transform": "norm_256_flip",
        "uid": "28c515a6ec9a8f93a19a2d06a2115c3d"
    },
    {
        "accuracy": 0.1839,
        "batch": 128,
        "duration": 1893403658,
        "lr": 0.00038386839529457045,
        "momentum": 0.19846887521645795,
        "transform": "echo",
        "uid": "c60dc7ea8fdb059c83cf874c84a64a9f"
    }
]