{
    "id": "f4e3248e1b74703ae9890bf4f4a1a59ee7c930548680fabc94e678ca957ca657",
    "enabled": true,
    "country": "US",
    "city": "Lackawanna County, Luzerne County",
    "location_summary": "United States, Pennsylvania, Lackawanna County, Luzerne County",
    "type": "bus",
    "transit_provider": "County of Lackawanna Transit System",
    "vehicle_positions_url": "https://coltsivl.availtec.com/InfoPoint/GTFS-Realtime.ashx?Type=VehiclePosition",
    "authentication_type": 0,
    "authentication_info_url": "",
    "api_key_parameter_name": "",
    "license_url": null,
    "vehicle_positions_url_type": "GTFS-Realtime",
    "refresh_interval": 30,
    "static_gtfs_url": "",
    "source_url": "https://mobilitydatabase.org/feeds/gtfs_rt/tld-4554-vp"
}