{
    "id": "1b54e9c62da577fc483bf7364357ea76fd52250fa04ff550ecd56de76b416168",
    "enabled": false,
    "country": "US",
    "city": "Windham County, Berkshire County, Bennington County",
    "location_summary": "United States, Vermont, Windham County, Berkshire County, Bennington County",
    "type": "bus",
    "transit_provider": "Green Mountain Community Network",
    "vehicle_positions_url": "https://api.goswift.ly/real-time/bennington-gmcn/gtfs-rt-vehicle-positions",
    "authentication_type": 2,
    "authentication_info_url": "https://goswift.ly/realtime-api-key",
    "api_key_parameter_name": "authorization",
    "license_url": "https://www.goswift.ly/api-license",
    "vehicle_positions_url_type": "GTFS-Realtime",
    "refresh_interval": 30,
    "static_gtfs_url": "",
    "source_url": "https://mobilitydatabase.org/feeds/gtfs_rt/mdb-1512"
}