[
    {
        "accuracy": 0.3488,
        "batch": 128,
        "dropout": 0.4,
        "lr": 0.01,
        "momentum": 0.95,
        "transform": "norm_256_flip",
        "uid": "494d3f8b5ef3e16f939d6a188a70b57c"
    },
    {
        "accuracy": 0.1609,
        "batch": 512,
        "dropout": 0.09519216968445515,
        "duration": 50269846385,
        "lr": 0.9531745034749128,
        "momentum": 0.6647826695909357,
        "transform": "norm_256_flip",
        "uid": "0e87f08705bbb108acb65356c8aed755"
    },
    {
        "accuracy": 0.1273,
        "batch": 8,
        "dropout": 0.34074779718722353,
        "duration": 62032874204,
        "lr": 6.685772856420353e-05,
        "momentum": 0.14642653559185037,
        "transform": "norm_299",
        "uid": "4bf90217154c36e22a52843dc0ea13d2"
    }
]