<?xml version="1.0" encoding="utf-8"?>
<registry xmlns:i18n="http://xml.zope.org/namespaces/i18n"
          i18n:domain="plone"
>

  <records interface="plone.app.querystring.interfaces.IQueryField"
           prefix="plone.app.querystring.field.tipologia_evento"
  >
    <value key="title"
           i18n:translate=""
    >Tipologia di evento</value>
    <value key="description"
           i18n:translate=""
    />
    <value key="enabled">True</value>
    <value key="sortable">False</value>
    <value key="operations">
      <element>plone.app.querystring.operation.selection.any</element>
      <element>plone.app.querystring.operation.selection.all</element>
    </value>
    <value key="vocabulary">collective.taxonomy.tipologia_evento</value>
    <value key="group"
           i18n:translate=""
    >Metadata</value>
  </records>

  <records interface="plone.app.querystring.interfaces.IQueryField"
           prefix="plone.app.querystring.field.tipologia_notizia"
  >
    <value key="title"
           i18n:translate=""
    >Tipologia notizia</value>
    <value key="description"
           i18n:translate=""
    >Tipologia della notizia</value>
    <value key="enabled">True</value>
    <value key="sortable">False</value>
    <value key="operations">
      <element>plone.app.querystring.operation.selection.any</element>
      <element>plone.app.querystring.operation.selection.all</element>
    </value>
    <value key="vocabulary">collective.taxonomy.tipologia_notizia</value>
    <value key="group"
           i18n:translate=""
    >Metadata</value>
  </records>

</registry>
